{
	"data": [
		{
			"name": "tulaytullah_s-remembrance",
			"rarity": 5,
			"limited": true,
			"weaponType": "catalyst"
		},
		{
			"name": "a-thousand-floating-dreams",
			"rarity": 5,
			"weaponType": "catalyst",
			"limited": true
		},
		{
			"name": "key-of-khaj-nisut",
			"rarity": 5,
			"weaponType": "sword",
			"limited": true
		},
		{
			"name": "xiphos-moonlight",
			"rarity": 4,
			"weaponType": "sword",
			"limited": true
		},
		{
			"name": "wandering-evenstar",
			"rarity": 4,
			"weaponType": "catalyst",
			"limited": true
		},
		{
			"name": "staff-of-the-scarlet-sands",
			"rarity": 5,
			"weaponType": "polearm",
			"limited": true
		},
		{
			"name": "makhaira-aquamarine",
			"rarity": 4,
			"weaponType": "claymore",
			"limited": true
		},
		{
			"name": "hunter_s-path",
			"rarity": 5,
			"weaponType": "bow",
			"limited": true
		},
		{
			"name": "aqua-simulacra",
			"rarity": 5,
			"weaponType": "bow",
			"limited": true
		},
		{
			"name": "redhorn-stonethresher",
			"rarity": 5,
			"weaponType": "claymore",
			"limited": true
		},
		{
			"name": "haran-geppaku-futsu",
			"rarity": 5,
			"weaponType": "sword",
			"limited": true
		},
		{
			"name": "kagura_s-verity",
			"rarity": 5,
			"weaponType": "catalyst",
			"limited": true
		},
		{
			"name": "calamity-queller",
			"rarity": 5,
			"weaponType": "polearm",
			"limited": true
		},
		{
			"name": "mouun_s-moon",
			"rarity": 4,
			"weaponType": "bow",
			"limited": true
		},
		{
			"name": "wavebreaker_s-fin",
			"rarity": 4,
			"weaponType": "polearm",
			"limited": true
		},
		{
			"name": "polar-star",
			"rarity": 5,
			"weaponType": "bow",
			"limited": true
		},
		{
			"name": "akuoumaru",
			"rarity": 4,
			"weaponType": "claymore",
			"limited": true
		},
		{
			"name": "everlasting-moonglow",
			"rarity": 5,
			"weaponType": "catalyst",
			"limited": true
		},
		{
			"name": "engulfing-lightning",
			"rarity": 5,
			"weaponType": "polearm",
			"limited": true
		},
		{
			"name": "thundering-pulse",
			"rarity": 5,
			"limited": true,
			"weaponType": "bow",
			"style": ""
		},
		{
			"name": "mistsplitter-reforged",
			"rarity": 5,
			"weaponType": "sword",
			"limited": true
		},
		{
			"name": "freedom-sworn",
			"rarity": 5,
			"weaponType": "sword",
			"limited": true
		},
		{
			"name": "mitternachts-waltz",
			"rarity": 4,
			"weaponType": "bow",
			"limited": true
		},
		{
			"name": "song-of-broken-pines",
			"rarity": 5,
			"weaponType": "claymore",
			"limited": true
		},
		{
			"name": "alley-hunter",
			"rarity": 4,
			"weaponType": "bow",
			"limited": true
		},
		{
			"name": "elegy-for-the-end",
			"rarity": 5,
			"weaponType": "bow",
			"limited": true
		},
		{
			"name": "the-alley-flash",
			"rarity": 4,
			"weaponType": "sword",
			"limited": true
		},
		{
			"name": "wine-and-song",
			"rarity": 4,
			"weaponType": "catalyst",
			"limited": true
		},
		{
			"name": "staff-of-homa",
			"rarity": 5,
			"weaponType": "polearm",
			"limited": true
		},
		{
			"name": "lithic-blade",
			"rarity": 4,
			"weaponType": "claymore",
			"limited": true
		},
		{
			"name": "lithic-spear",
			"rarity": 4,
			"weaponType": "polearm",
			"limited": true
		},
		{
			"name": "primordial-jade-cutter",
			"rarity": 5,
			"weaponType": "sword",
			"limited": true
		},
		{
			"name": "primordial-jade-winged-spear",
			"rarity": 5,
			"weaponType": "polearm"
		},
		{
			"name": "summit-shaper",
			"rarity": 5,
			"weaponType": "sword",
			"limited": true
		},
		{
			"name": "vortex-vanquisher",
			"rarity": 5,
			"weaponType": "polearm",
			"limited": true
		},
		{
			"name": "the-unforged",
			"rarity": 5,
			"weaponType": "claymore",
			"limited": true
		},
		{
			"name": "memory-of-dust",
			"rarity": 5,
			"weaponType": "catalyst",
			"limited": true
		},
		{
			"name": "eye-of-perception",
			"rarity": 4,
			"weaponType": "catalyst"
		},
		{
			"name": "rainslasher",
			"rarity": 4,
			"weaponType": "claymore"
		},
		{
			"name": "rust",
			"rarity": 4,
			"weaponType": "bow"
		},
		{
			"name": "lost-prayer-to-the-sacred-winds",
			"rarity": 5,
			"weaponType": "catalyst"
		},
		{
			"name": "wolf_s-gravestone",
			"rarity": 5,
			"weaponType": "claymore"
		},
		{
			"name": "amos-bow",
			"rarity": 5,
			"weaponType": "bow"
		},
		{
			"name": "aquila-favonia",
			"rarity": 5,
			"weaponType": "sword"
		},
		{
			"name": "skyward-pride",
			"rarity": 5,
			"weaponType": "claymore"
		},
		{
			"name": "skyward-atlas",
			"rarity": 5,
			"weaponType": "catalyst",
			"style": "left: 80%"
		},
		{
			"name": "skyward-harp",
			"rarity": 5,
			"weaponType": "bow"
		},
		{
			"name": "skyward-spine",
			"rarity": 5,
			"weaponType": "polearm"
		},
		{
			"name": "skyward-blade",
			"rarity": 5,
			"weaponType": "sword"
		},
		{
			"name": "the-flute",
			"rarity": 4,
			"weaponType": "sword"
		},
		{
			"name": "the-widsith",
			"rarity": 4,
			"weaponType": "catalyst"
		},
		{
			"name": "dragon_s-bane",
			"rarity": 4,
			"weaponType": "polearm"
		},
		{
			"name": "lion_s-roar",
			"rarity": 4,
			"weaponType": "sword"
		},
		{
			"name": "sacrificial-bow",
			"rarity": 4,
			"weaponType": "bow"
		},
		{
			"name": "sacrificial-fragments",
			"rarity": 4,
			"weaponType": "catalyst"
		},
		{
			"name": "sacrificial-greatsword",
			"rarity": 4,
			"weaponType": "claymore"
		},
		{
			"name": "sacrificial-sword",
			"rarity": 4,
			"weaponType": "sword"
		},
		{
			"name": "favonius-greatsword",
			"rarity": 4,
			"weaponType": "claymore"
		},
		{
			"name": "favonius-sword",
			"rarity": 4,
			"weaponType": "sword"
		},
		{
			"name": "favonius-warbow",
			"rarity": 4,
			"weaponType": "bow"
		},
		{
			"name": "favonius-codex",
			"rarity": 4,
			"weaponType": "catalyst"
		},
		{
			"name": "favonius-lance",
			"rarity": 4,
			"weaponType": "polearm"
		},
		{
			"name": "the-bell",
			"rarity": 4,
			"weaponType": "claymore"
		},
		{
			"name": "the-stringless",
			"rarity": 4,
			"weaponType": "bow"
		},
		{
			"name": "black-tassel",
			"rarity": 3,
			"weaponType": "polearm"
		},
		{
			"name": "bloodtained-greatsword",
			"rarity": 3,
			"weaponType": "claymore"
		},
		{
			"name": "cool-steel",
			"rarity": 3,
			"weaponType": "sword"
		},
		{
			"name": "debate-club",
			"rarity": 3,
			"weaponType": "claymore"
		},
		{
			"name": "emerald-orb",
			"rarity": 3,
			"weaponType": "catalyst"
		},
		{
			"name": "ferrous-shadow",
			"rarity": 3,
			"weaponType": "claymore"
		},
		{
			"name": "harbinger-of-dawn",
			"rarity": 3,
			"weaponType": "sword"
		},
		{
			"name": "magic-guide",
			"rarity": 3,
			"weaponType": "catalyst"
		},
		{
			"name": "raven-bow",
			"rarity": 3,
			"weaponType": "bow"
		},
		{
			"name": "sharpshooter_s-oath",
			"rarity": 3,
			"weaponType": "bow"
		},
		{
			"name": "skyrider-sword",
			"rarity": 3,
			"weaponType": "sword"
		},
		{
			"name": "slingshot",
			"rarity": 3,
			"weaponType": "bow"
		},
		{
			"name": "thrilling-tales-of-dragon-slayers",
			"rarity": 3,
			"weaponType": "catalyst"
		}
	]
}
